{
  "18歲前居住地": "桃園市楊梅區",
  "id": 235633,
  "內容類型": "錄音稿",
  "客語拼音": "kad5 chud5 ciong11 gong11 kim55 rhong33 gai11 vu53 kien33 lau53 pag2 kien33 ， biong11 di11 shu53 zog5 mien11 hong33 zhun24 gong11 kim55 rhung33 ，",
  "客語漢字": "刻出像鋼琴樣个烏鍵摎白鍵，放在書桌面項準鋼琴用，",
  "年齡": 52,
  "性別": "女性",
  "提示卡編號": "H1072",
  "教育程度": "研究所",
  "流暢度": "普通",
  "現居地": "桃園市中壢區",
  "發音員編號": "HF370",
  "華語字": "刻進像鋼琴一樣的黑鍵和白鍵，放在書桌上面當鋼琴用，",
  "語言背景": "",
  "身分別": "薪傳師（教師）",
  "錄音環境": "一般辦公室",
  "錄音腔調": "海陸",
  "音檔編號": 13,
  "音檔長度": "13.59"
}