{
  "18歲前居住地": "新北市土城區",
  "id": 156372,
  "內容類型": "錄音稿",
  "客語拼音": "on53 pai55 do11 cin33 to55 dong11 。 giag5 loi55 ten11 pad5 fo24 。 ma24 ngin55 do11 gai55 pong53 mun55 ？ sai24 zeu24 。 ngiau11 sai24 deu11 。",
  "客語漢字": "安排到盡妥當。遽來𢯭撥火。麼人在該碰門？徙走。貓徙竇。",
  "年齡": 38,
  "性別": "女性",
  "提示卡編號": "G1001",
  "教育程度": "研究所",
  "流暢度": "普通",
  "現居地": "新竹縣竹北市",
  "發音員編號": "HF308",
  "華語字": "安排得很妥當。快來幫忙搧火。誰在那裡用力敲門？搬走。母貓生小貓後，若是發現環境對小貓有危險就馬上將小貓銜至較安全處；用以比喻一個人在生活或工作上不甚穩定，常有調動。",
  "語言背景": "",
  "身分別": "薪傳師（教師）",
  "錄音環境": "一般辦公室",
  "錄音腔調": "海陸",
  "音檔編號": 150,
  "音檔長度": "16.62"
}