{
  "18歲前居住地": "新竹縣橫山鄉",
  "id": 169061,
  "內容類型": "錄音稿",
  "客語拼音": "gong24 do24 nung55 ngiab2 han55 mang55 rhiu53 gi53 hai24 fa11 gai11 ngien55 toi33 ， shi33 tien55 god5 vo55 rhid5 mad5 sad5 ciu33 oi11 ngin55 gung53 。",
  "客語漢字": "講著農業還吂有機械化个年代，蒔田割禾一抹煞就愛人工。",
  "年齡": 69,
  "性別": "女性",
  "提示卡編號": "H1063",
  "教育程度": "高中",
  "流暢度": "流暢",
  "現居地": "桃園市龍潭區",
  "發音員編號": "HF325",
  "華語字": "說到農業還沒有機械化的年代，插秧割稻全部都需要人力。",
  "語言背景": "",
  "身分別": "薪傳師（教師）",
  "錄音環境": "一般辦公室",
  "錄音腔調": "海陸",
  "音檔編號": 39,
  "音檔長度": "13.62"
}