{
  "18歲前居住地": "桃園市新屋區",
  "id": 246887,
  "內容類型": "錄音稿",
  "客語拼音": "a33 go53 rhid5 zhong53 zhoi11 dong53 voi33 au11 ， ngi55 au11 m55 rhang55 gi55 。 min55 min55 cid5 ga53 m55 chog2 ， gi55 han55 gin24 au11 。 ",
  "客語漢字": "阿哥一張嘴當會詏，你詏毋贏佢。明明自家毋著，佢還緊詏。",
  "年齡": 72,
  "性別": "女性",
  "提示卡編號": "G1114",
  "教育程度": "五專",
  "流暢度": "流暢",
  "現居地": "桃園市中壢區",
  "發音員編號": "HF386",
  "華語字": "哥哥一張嘴很會辯駁，你辯不贏他。明明自己不對，他還一直辯駁。",
  "語言背景": "",
  "身分別": "薪傳師（教師）",
  "錄音環境": "一般辦公室",
  "錄音腔調": "海陸",
  "音檔編號": 138,
  "音檔長度": "13.56"
}