{
  "18歲前居住地": "新竹縣湖口鄉",
  "id": 178945,
  "內容類型": "錄音稿",
  "客語拼音": "gim53 ngien55 shiu53 ngib2 gam24 shau24 i53 do53 。 gi55 shong33 li53 bai11 li55 koi53 toi55 van53 。 lo24 moi11 dui11 gia11 dang24 liu11 ha53 loi55 。 ",
  "客語漢字": "今年收入減少已多。佢上禮拜離開臺灣。老妹對崎頂溜下來。",
  "年齡": 68,
  "性別": "男性",
  "提示卡編號": "G1074",
  "教育程度": "研究所",
  "流暢度": "流暢",
  "現居地": "新竹縣湖口鄉",
  "發音員編號": "HM323",
  "華語字": "今年收入減少很多。他上星期離開臺灣。妹妹從坡頂滑下來。",
  "語言背景": "",
  "身分別": "薪傳師（教師）",
  "錄音環境": "一般辦公室",
  "錄音腔調": "海陸",
  "音檔編號": 138,
  "音檔長度": "16.44"
}