{
  "18歲前居住地": "新竹縣關西鎮",
  "id": 255866,
  "內容類型": "錄音稿",
  "客語拼音": "ngiu55 m55 zo11 ， ced2 er55 m55 zo11 ， vang55 da24 chid2 go11 。 gi55 gai11 gung53 fu53 i53 do11 ga53 ， zo11 ded5 chud5 sii53 le53 。",
  "客語漢字": "牛毋做，賊仔毋做，橫打直過。佢个功夫已到家，做得出師咧。",
  "年齡": 53,
  "性別": "女性",
  "提示卡編號": "G1129",
  "教育程度": "研究所",
  "流暢度": "普通",
  "現居地": "嘉義市西區",
  "發音員編號": "HF357",
  "華語字": "不當奴役，不偷東西，就可大大方方走大路。他的功夫很到家，可以出師了。",
  "語言背景": "",
  "身分別": "薪傳師（教師）",
  "錄音環境": "一般辦公室",
  "錄音腔調": "海陸",
  "音檔編號": 143,
  "音檔長度": "14.87"
}