{
  "18歲前居住地": "桃園市新屋區",
  "id": 161726,
  "內容類型": "錄音稿",
  "客語拼音": "san53 ngiau11 ne53 ！ toi55 van55 gai11 piang55 ti33 rhiu24 kon11 ded5 do24 san53 ngiau11 le53 ， han55 zeu24 hi11 a33 ze55 gai11 gai53 zi11 nau33 gieu24 ，",
  "客語漢字": "山貓呢！臺灣个平地又看得著山貓咧，還走去阿姊个雞塒鬧狗，",
  "年齡": 58,
  "性別": "女性",
  "提示卡編號": "H1015",
  "教育程度": "研究所",
  "流暢度": "普通",
  "現居地": "桃園市楊梅區",
  "發音員編號": "HF323",
  "華語字": "山貓呢！臺灣的平地又看得到山貓了，還跑去姊姊的雞舍胡鬧，",
  "語言背景": "",
  "身分別": "薪傳師（教師）",
  "錄音環境": "一般辦公室",
  "錄音腔調": "海陸",
  "音檔編號": 28,
  "音檔長度": "12.12"
}