{
  "18歲前居住地": "花蓮縣花蓮市",
  "id": 203967,
  "內容類型": "錄音稿",
  "客語拼音": "lau53 gi55 gieu53 tung53 gia33 bai24 ， han55 he11 kiung33 rhong33 。 he11 zo11 m55 do24 ciu33 m55 ho24 cin24 cai24 rhin24 shin55 ngin55 。 ",
  "客語漢字": "摎佢溝通幾下擺，還係共樣。係做毋著就毋好儘採應承人。",
  "年齡": 68,
  "性別": "女性",
  "提示卡編號": "G1098",
  "教育程度": "研究所",
  "流暢度": "普通",
  "現居地": "桃園市八德區",
  "發音員編號": "HF358",
  "華語字": "跟他溝通好幾次，還是一樣。如果做不到就不要隨便承諾別人。",
  "語言背景": "",
  "身分別": "薪傳師（教師）",
  "錄音環境": "一般辦公室",
  "錄音腔調": "海陸",
  "音檔編號": 142,
  "音檔長度": "11.91"
}