{
  "18歲前居住地": "新竹縣竹東鎮",
  "id": 194980,
  "內容類型": "錄音稿",
  "客語拼音": "lia55 man53 e11 ngin55 dong53 shi55 hang55 du11 miong24 zham11 kon11 sin53 vun55 。hon55 liu55 loi55 ， lang53 fung53 chui53 do24 ngin55 gin24 da24 gid5 zhun53 。",
  "客語漢字": "這滿个人當時行在網站看新聞。寒流來，冷風吹著人緊打激顫。",
  "年齡": 62,
  "性別": "男性",
  "提示卡編號": "G1014",
  "教育程度": "五專",
  "流暢度": "普通",
  "現居地": "新竹縣竹北市",
  "發音員編號": "HM315",
  "華語字": "現在的人很流行在網站上瀏覽新聞。寒流來，冷風吹到人直打冷顫。",
  "語言背景": "",
  "身分別": "民眾",
  "錄音環境": "一般辦公室",
  "錄音腔調": "海陸",
  "音檔編號": 143,
  "音檔長度": "11.28"
}