{
  "18歲前居住地": "新竹縣竹北市",
  "id": 200762,
  "內容類型": "錄音稿",
  "客語拼音": "gi55 sen53 lau53 zag5 zhon24 loi55 gai11 chong55 teu33 er55 rhung33 ciang33 shui24 se24 ciang33 loi55 ，den24 tai33 vog2 teu55 gai11 shui24 gun24 le53 ，",
  "客語漢字": "佢先摎摘轉來个長豆仔用淨水洗淨來，等大鑊頭个水滾咧，",
  "年齡": 59,
  "性別": "男性",
  "提示卡編號": "H1097",
  "教育程度": "大學",
  "流暢度": "流暢",
  "現居地": "新竹縣竹北市",
  "發音員編號": "HM333",
  "華語字": "她先把採回來的長豇豆用乾淨水洗乾淨，等大鍋的水煮滾，",
  "語言背景": "",
  "身分別": "薪傳師（教師）",
  "錄音環境": "一般辦公室",
  "錄音腔調": "海陸",
  "音檔編號": 20,
  "音檔長度": "12.56"
}