{
  "18歲前居住地": "新竹縣湖口鄉",
  "id": 218336,
  "內容類型": "錄音稿",
  "客語拼音": "sai11 ham55 tam53 ， lia24 gien24 dan53 gai11 sam53 zhag5 sii33 ，mo55 xiong24 do24 rhiu53 an24 do53 gai11 gin53 ngiam33 lau53 zhi11 fui33 di11 di53 boi11 ！",
  "客語漢字": "晒鹹淡，這簡單个三隻字，無想著有恁多个經驗摎智慧在裡背！",
  "年齡": 67,
  "性別": "女性",
  "提示卡編號": "H1099",
  "教育程度": "大學",
  "流暢度": "普通",
  "現居地": "新北市樹林區",
  "發音員編號": "HF351",
  "華語字": "曬菜乾，這簡單的三個字，沒想到有這麼多的經驗和智慧在裡面！",
  "語言背景": "",
  "身分別": "薪傳師（教師）",
  "錄音環境": "一般辦公室",
  "錄音腔調": "海陸",
  "音檔編號": 33,
  "音檔長度": "14.22"
}