{
  "18歲前居住地": "桃園市中壢區",
  "id": 160076,
  "內容類型": "錄音稿",
  "客語拼音": "lia24 zied5 mug5 dong53 zin53 cai24 ， ngi55 loi55 kiung33 ha33 kon11 。 gi55 kau24 do24 bog5 sii33 ban53 ， gia55 rha55 oi53 dong53 tiong11 。 ",
  "客語漢字": "這節目當精彩，你來共下看。佢考著博士班，厥爺哀當暢。",
  "年齡": 69,
  "性別": "女性",
  "提示卡編號": "G1037",
  "教育程度": "高中",
  "流暢度": "流暢",
  "現居地": "桃園市中壢區",
  "發音員編號": "HF319",
  "華語字": "這節目很精采，你來一起看。他考上博士班，他父母很開心。",
  "語言背景": "",
  "身分別": "薪傳師（教師）",
  "錄音環境": "一般辦公室",
  "錄音腔調": "海陸",
  "音檔編號": 142,
  "音檔長度": "11.94"
}