{
  "18歲前居住地": "桃園市新屋區",
  "id": 174436,
  "內容類型": "錄音稿",
  "客語拼音": "gi55 lia24 zag5 ngin55 dong53 rhiu53 nai33 sim53 。 ngi55 ngiong24 mien11 sed5 an24 nan33 kon11 no33 ？ ci55 ba53 dong53 ngion53 ， dong53 ho24 siid2 。",
  "客語漢字": "佢這隻人當有耐心。你仰面色恁難看呢？粢粑當軟，當好食。",
  "年齡": 59,
  "性別": "女性",
  "提示卡編號": "G1064",
  "教育程度": "大學",
  "流暢度": "普通",
  "現居地": "桃園市中壢區",
  "發音員編號": "HF333",
  "華語字": "他這個人很有耐心。你的臉色怎麼這麼難看呢？麻糬很軟，很好吃。",
  "語言背景": "",
  "身分別": "薪傳師（教師）",
  "錄音環境": "一般辦公室",
  "錄音腔調": "海陸",
  "音檔編號": 147,
  "音檔長度": "13.06"
}